minio_client/__init__.py
minio_client-1.0.0.dist-info/METADATA
minio_client-1.0.0.dist-info/WHEEL
minio_client-1.0.0.dist-info/licenses/LICENSE
minio_client-1.0.0.dist-info/RECORD
