Metadata-Version: 2.4
Name: minio-client
Version: 1.0.0
Summary: MinIO client tools.
Project-URL: Repository, https://github.com/clydecbrown/minio-client
Author-email: Clyde C Brown <clyde.c.brown@pm.me>
License: MIT
License-File: LICENSE
Keywords: minio,networking
Classifier: Development Status :: 5 - Production/Stable
Classifier: Intended Audience :: Developers
Classifier: License :: OSI Approved :: MIT License
Classifier: Natural Language :: English
Classifier: Operating System :: OS Independent
Classifier: Programming Language :: Python :: 3.10
Classifier: Programming Language :: Python :: 3.11
Classifier: Programming Language :: Python :: 3.12
Classifier: Programming Language :: Python :: 3.13
Classifier: Programming Language :: Python :: 3.14
Classifier: Topic :: Software Development :: Libraries :: Python Modules
Classifier: Topic :: System :: Networking
Classifier: Typing :: Typed
Requires-Python: >=3.10
Requires-Dist: func-timeout>=4.3.5
Requires-Dist: minio>=7.1.2
